dinesh/__init__.py
dinesh/dinesh.py
dinesh-0.1.dist-info/METADATA
dinesh-0.1.dist-info/WHEEL
dinesh-0.1.dist-info/top_level.txt
dinesh-0.1.dist-info/RECORD
