Metadata-Version: 2.1
Name: dinesh
Version: 0.1
Summary: For Noopur
Home-page: UNKNOWN
Author: Dinesh Maharana
Author-email: dinesh.cse31@gmail.com
License: MIT
Platform: UNKNOWN
